async_django_user/aiohttp.py
async_django_user/asyncpg.py
async_django_user/base_backend.py
async_django_user/databases.py
async_django_user/hashers.py
async_django_user/starlette.py
async_django_user/user.py
async_django_user/utils.py
async_django_user-0.2.0.dist-info/METADATA
async_django_user-0.2.0.dist-info/WHEEL
async_django_user-0.2.0.dist-info/top_level.txt
async_django_user-0.2.0.dist-info/RECORD
