Metadata-Version: 2.1
Name: async-django-user
Version: 0.2.0
Summary: Django user for async frameworks
Home-page: https://github.com/imbolc/async-django-user
Author: Imbolc
Author-email: imbolc@imbolc.name
License: MIT
Platform: UNKNOWN
Classifier: Development Status :: 4 - Beta
Classifier: License :: OSI Approved :: MIT License
Classifier: Programming Language :: Python :: 3
Classifier: Operating System :: OS Independent
